README
setup.py
txJsonRpc_Netstrings.egg-info/PKG-INFO
txJsonRpc_Netstrings.egg-info/SOURCES.txt
txJsonRpc_Netstrings.egg-info/dependency_links.txt
txJsonRpc_Netstrings.egg-info/top_level.txt
txjsonrpc_netstrings/__init__.py
txjsonrpc_netstrings/jsonrpc.py
txjsonrpc_netstrings/jsonrpclib.py