Metadata-Version: 1.0
Name: txJsonRpc-Netstrings
Version: 0.2a1
Summary: Lightweight json-rpc library for building Twisted-based TCP (Netstring) clients and servers
Home-page: http://github.com/teltech/txJsonRpc-Netstrings
Author: TelTech Systems
Author-email: UNKNOWN
License: UNKNOWN
Platform: UNKNOWN
